README.md
setup.py
harmony_tools/__init__.py
harmony_tools/gammas.py
harmony_tools/notes.py
harmony_tools/pentatonics.py
harmony_tools.egg-info/PKG-INFO
harmony_tools.egg-info/SOURCES.txt
harmony_tools.egg-info/dependency_links.txt
harmony_tools.egg-info/entry_points.txt
harmony_tools.egg-info/top_level.txt
harmony_tools/cli/__init__.py
harmony_tools/cli/argparser.py
harmony_tools/cli/abc/__init__.py
harmony_tools/cli/abc/category.py
harmony_tools/cli/abc/command.py
harmony_tools/cli/categories/__init__.py
harmony_tools/cli/categories/gammas/__init__.py
harmony_tools/cli/categories/gammas/detect.py
harmony_tools/cli/categories/guitar/__init__.py
harmony_tools/cli/categories/guitar/show_gamma.py
harmony_tools/cli/categories/guitar/show_neck.py
harmony_tools/cli/categories/guitar/show_pentatonic.py
harmony_tools/cli/categories/notes/__init__.py
harmony_tools/cli/categories/notes/random.py
harmony_tools/cli/categories/pentatonics/__init__.py
harmony_tools/cli/categories/pentatonics/detect.py
harmony_tools/core/__init__.py
harmony_tools/core/colors.py
harmony_tools/core/gamma_structure.py
harmony_tools/core/note_operations.py
harmony_tools/core/pentatonic_structure.py
tests/__init__.py
tests/test_gammas.py