Metadata-Version: 2.1
Name: harmony-tools
Version: 0.1
Summary: UNKNOWN
Home-page: https://github.com/a1fred/harmony_tools
Author: a1fred
Author-email: demalf@gmail.com
License: MIT
Platform: UNKNOWN
Classifier: Environment :: Console
Classifier: Operating System :: POSIX :: Linux
Classifier: Operating System :: MacOS :: MacOS X
Classifier: Development Status :: 5 - Production/Stable
Classifier: Programming Language :: Python :: 3.7
